pts_cli/__init__.py
pts_cli/__main__.py
pts_cli/bap.py
pts_cli-0.1.1.dist-info/METADATA
pts_cli-0.1.1.dist-info/WHEEL
pts_cli-0.1.1.dist-info/entry_points.txt
pts_cli-0.1.1.dist-info/top_level.txt
pts_cli-0.1.1.dist-info/RECORD
